python_mcstatus/__about__.py
python_mcstatus/__init__.py
python_mcstatus/constants.py
python_mcstatus/status.py
python_mcstatus-0.0.2.dist-info/METADATA
python_mcstatus-0.0.2.dist-info/WHEEL
python_mcstatus-0.0.2.dist-info/licenses/LICENSE
python_mcstatus-0.0.2.dist-info/RECORD
