Metadata-Version: 2.1
Name: python-mcstatus
Version: 0.0.2
Summary: The unofficial python library for interacting with the mcstatus.io API.
Project-URL: Documentation, https://github.com/Duve3/python-mcstatus#readme
Project-URL: Issues, https://github.com/Duve3/python-mcstatus/issues
Project-URL: Source, https://github.com/Duve3/python-mcstatus
Author-email: Duve3 <Duv3tabest@gmail.com>
License-Expression: MIT
License-File: LICENSE
Classifier: Development Status :: 4 - Beta
Classifier: Programming Language :: Python
Classifier: Programming Language :: Python :: 3.9
Classifier: Programming Language :: Python :: 3.10
Classifier: Programming Language :: Python :: 3.11
Classifier: Programming Language :: Python :: Implementation :: CPython
Classifier: Programming Language :: Python :: Implementation :: PyPy
Requires-Python: >=3.9
Requires-Dist: requests~=2.31.0
